playfromtext/__init__.py
playfromtext/play_it.py
playfromtext-0.1.dist-info/LICENCE
playfromtext-0.1.dist-info/METADATA
playfromtext-0.1.dist-info/WHEEL
playfromtext-0.1.dist-info/entry_points.txt
playfromtext-0.1.dist-info/top_level.txt
playfromtext-0.1.dist-info/RECORD
